ttf2web.py
ttf2web-0.9.3.dist-info/DESCRIPTION.rst
ttf2web-0.9.3.dist-info/METADATA
ttf2web-0.9.3.dist-info/RECORD
ttf2web-0.9.3.dist-info/WHEEL
ttf2web-0.9.3.dist-info/entry_points.txt
ttf2web-0.9.3.dist-info/metadata.json
ttf2web-0.9.3.dist-info/top_level.txt
