Metadata-Version: 2.0
Name: ttf2web
Version: 0.9.3
Summary: A tool to optimize fonts for web distribution.
Home-page: https://github.com/johncf/ttf2web
Author: John C F
Author-email: john.ch.fr@gmail.com
License: MIT
Keywords: ttf woff2 webfont converter splitter css
Platform: UNKNOWN
Classifier: Development Status :: 4 - Beta
Classifier: Intended Audience :: Developers
Classifier: Topic :: Text Processing :: Fonts
Classifier: Topic :: Utilities
Classifier: Environment :: Web Environment
Classifier: License :: OSI Approved :: MIT License
Classifier: Programming Language :: Python :: 3
Classifier: Programming Language :: Python :: 3.4
Classifier: Programming Language :: Python :: 3.5
Classifier: Programming Language :: Python :: 3.6
Requires-Dist: fonttools
